st_joystick/__init__.py
st_joystick/frontend/index.html
st_joystick/frontend/main.js
st_joystick/frontend/package-lock.json
st_joystick/frontend/package.json
st_joystick/frontend/style.css
st_joystick/frontend/build/frontend.d11ba8e3.js
st_joystick/frontend/build/frontend.d11ba8e3.js.map
st_joystick/frontend/build/frontend.ed3a7e8f.css
st_joystick/frontend/build/frontend.ed3a7e8f.css.map
st_joystick/frontend/build/index.html
streamlit_joystick-0.1.1.dist-info/licenses/LICENSE
streamlit_joystick-0.1.1.dist-info/METADATA
streamlit_joystick-0.1.1.dist-info/WHEEL
streamlit_joystick-0.1.1.dist-info/top_level.txt
streamlit_joystick-0.1.1.dist-info/RECORD
