Metadata-Version: 2.4
Name: streamlit-joystick
Version: 0.1.1
Summary: This component allows you to have a joystick in streamlit
Home-page: https://pypi.org/project/streamlit-joystick/
Author: Ephson Guakro
Author-email: leocorp96@gmail.com
Requires-Python: >=3.7
License-File: LICENSE
Requires-Dist: streamlit>=1.2
Requires-Dist: jinja2
Dynamic: author
Dynamic: author-email
Dynamic: description
Dynamic: description-content-type
Dynamic: home-page
Dynamic: license-file
Dynamic: requires-dist
Dynamic: requires-python
Dynamic: summary
